nautobot_firewall_models/__init__.py
nautobot_firewall_models/api/__init__.py
nautobot_firewall_models/api/serializers.py
nautobot_firewall_models/api/urls.py
nautobot_firewall_models/api/views.py
nautobot_firewall_models/app-config-schema.json
nautobot_firewall_models/choices.py
nautobot_firewall_models/constants.py
nautobot_firewall_models/details.py
nautobot_firewall_models/fields.py
nautobot_firewall_models/filters.py
nautobot_firewall_models/forms.py
nautobot_firewall_models/homepage.py
nautobot_firewall_models/jobs.py
nautobot_firewall_models/management/__init__.py
nautobot_firewall_models/management/commands/__init__.py
nautobot_firewall_models/management/commands/create_test_firewall_data.py
nautobot_firewall_models/migrations/0001_initial.py
nautobot_firewall_models/migrations/0002_custom_status.py
nautobot_firewall_models/migrations/0003_default_status.py
nautobot_firewall_models/migrations/0004_add_description.py
nautobot_firewall_models/migrations/0005_capircapolicy.py
nautobot_firewall_models/migrations/0006_renaming_part1.py
nautobot_firewall_models/migrations/0007_renaming_part2.py
nautobot_firewall_models/migrations/0008_renaming_part3.py
nautobot_firewall_models/migrations/0009_proper_ordering_on_through.py
nautobot_firewall_models/migrations/0010_nat_policy.py
nautobot_firewall_models/migrations/0011_custom_status_nat.py
nautobot_firewall_models/migrations/0012_remove_status_m2m_through_models.py
nautobot_firewall_models/migrations/0013_applications.py
nautobot_firewall_models/migrations/0014_custom_status_application.py
nautobot_firewall_models/migrations/0015_alter_capircapolicy_device.py
nautobot_firewall_models/migrations/0016_nautobot_v2_migrations.py
nautobot_firewall_models/migrations/0017_resolve_issues_through_tables_part1.py
nautobot_firewall_models/migrations/0018_resolve_issues_through_tables_part2.py
nautobot_firewall_models/migrations/0019_resolve_issues_through_tables_part3.py
nautobot_firewall_models-3.0.0.dist-info/LICENSE
nautobot_firewall_models-3.0.0.dist-info/METADATA
nautobot_firewall_models-3.0.0.dist-info/WHEEL
nautobot_firewall_models-3.0.0.dist-info/RECORD
