Metadata-Version: 2.3
Name: nautobot-firewall-models
Version: 3.0.0
Summary: Nautobot app to model firewall objects.
License: Apache-2.0
Keywords: nautobot,nautobot-app,nautobot-plugin
Author: Network to Code, LLC
Author-email: opensource@networktocode.com
Requires-Python: >=3.10,<3.14
Classifier: Development Status :: 5 - Production/Stable
Classifier: Intended Audience :: Developers
Classifier: License :: OSI Approved :: Apache Software License
Classifier: Programming Language :: Python :: 3
Classifier: Programming Language :: Python :: 3.10
Classifier: Programming Language :: Python :: 3.11
Classifier: Programming Language :: Python :: 3.12
Classifier: Programming Language :: Python :: 3.13
Provides-Extra: all
Requires-Dist: capirca (>=2.0.6,<3.0.0)
Requires-Dist: nautobot (>=3.0.0,<4.0.0)
Project-URL: Documentation, https://docs.nautobot.com/projects/firewall-models/en/latest/
Project-URL: Homepage, https://github.com/nautobot/nautobot-app-firewall-models
Project-URL: Repository, https://github.com/nautobot/nautobot-app-firewall-models
